{
    "author": {
        "date": "2009-06-17 03:01:48",
        "description": "Cosplayer ✨Spicy Model ✨ Cat Mom ✨ (っ◔◡◔)っ ⬇️⬇️⬇️ for the good stuff!",
        "favourites_count": 10588,
        "followers_count": 598659,
        "friends_count": 546,
        "id": 47833190,
        "listed_count": 1123,
        "location": "",
        "media_count": 4821,
        "name": "kristenlanae",
        "nick": "Kristen Lanae",
        "profile_banner": "https://pbs.twimg.com/profile_banners/47833190/1643274346",
        "profile_image": "https://pbs.twimg.com/profile_images/1545535947621556224/7tGKpKJT.jpg",
        "statuses_count": 33221,
        "url": "http://kristenlanae.com",
        "verified": true
    },
    "category": "twitter",
    "content": "always wear your seat belt 😉",
    "date": "2022-07-08 21:02:38",
    "favorite_count": 7055,
    "lang": "en",
    "quote_count": 4,
    "quote_id": 0,
    "reply_count": 90,
    "reply_id": 0,
    "retweet_count": 392,
    "retweet_id": 0,
    "subcategory": "tweet",
    "tweet_id": 1545513712630452224,
    "user": {
        "date": "2009-06-17 03:01:48",
        "description": "Cosplayer ✨Spicy Model ✨ Cat Mom ✨ (っ◔◡◔)っ ⬇️⬇️⬇️ for the good stuff!",
        "favourites_count": 10588,
        "followers_count": 598659,
        "friends_count": 546,
        "id": 47833190,
        "listed_count": 1123,
        "location": "",
        "media_count": 4821,
        "name": "kristenlanae",
        "nick": "Kristen Lanae",
        "profile_banner": "https://pbs.twimg.com/profile_banners/47833190/1643274346",
        "profile_image": "https://pbs.twimg.com/profile_images/1545535947621556224/7tGKpKJT.jpg",
        "statuses_count": 33221,
        "url": "http://kristenlanae.com",
        "verified": true
    }
}
